aas_thing/__init__.py
aas_thing/aas_connection.py
aas_thing/core.py
aas_thing/message_handler.py
aas_thing/s3i_connection.py
aas_thing/s3i/__init__.py
aas_thing/s3i/broker.py
aas_thing/s3i/directory.py
aas_thing/s3i/identity_provider.py
aas_thing/s3i/repository.py
aas_thing/s3i/message/__init__.py
aas_thing/s3i/message/event.py
aas_thing/s3i/message/frame.py
aas_thing/s3i/message/get_submodel_element_by_path.py
aas_thing/s3i/message/invoke_operation.py
aas_thing/s3i/message/message.py
aas_thing/s3i/message/model.py
aas_thing/s3i/message/reference.py
aas_thing/s3i/message/schema.py
aas_thing/util/__init__.py
aas_thing/util/callback_manager.py
aas_thing/util/json_validator.py
aas_thing/util/logger.py
aas_thing/util/open_config_yaml.py
aas_thing-0.9.7.dist-info/licenses/LICENSE
aas_thing-0.9.7.dist-info/METADATA
aas_thing-0.9.7.dist-info/WHEEL
aas_thing-0.9.7.dist-info/top_level.txt
aas_thing-0.9.7.dist-info/RECORD
