Metadata-Version: 2.4
Name: aas-thing
Version: 0.9.7
Summary: A Python toolkit for building Industry 4.0-compliant Things as Asset Administration Shells (AAS), with seamless integration into the Smart Systems Service Infrastructure (S³I).
Author-email: The S3I Development Team <s3i@kwh40.de>
License-Expression: LGPL-3.0-only
Requires-Python: >=3.9
License-File: LICENSE
Requires-Dist: pytest>=7.0
Requires-Dist: pika==1.3.2
Requires-Dist: python-keycloak
Requires-Dist: basyx-python-sdk==1.2.0
Requires-Dist: pyyaml
Requires-Dist: jsonschema
Requires-Dist: aas-python-http-client==1.0.2
Requires-Dist: pydantic
Provides-Extra: docs
Requires-Dist: Sphinx==5.0.2; extra == "docs"
Requires-Dist: recommonmark==0.6.0; extra == "docs"
Requires-Dist: sphinx_rtd_theme; extra == "docs"
Requires-Dist: sphinx-tabs; extra == "docs"
Requires-Dist: sphinxcontrib-images; extra == "docs"
Dynamic: license-file
